rl_sdk/__init__.py
rl_sdk/event_handling.py
rl_sdk/events.py
rl_sdk/frida_script.py
rl_sdk/game_objects.py
rl_sdk/sdk.py
rlapi/__init__.py
rlapi/event_handling.py
rlapi/events.py
rlapi/frida_script.py
rlapi/game_objects.py
rlapi/sdk.py
rlkit/__init__.py
rlkit/event_handling.py
rlkit/events.py
rlkit/frida_script.py
rlkit/game_objects.py
rlkit/sdk.py
rlsdk_py/__init__.py
rlsdk_py/event_handling.py
rlsdk_py/events.py
rlsdk_py/frida_script.py
rlsdk_py/game_objects.py
rlsdk_py/sdk.py
rocketlib/__init__.py
rocketlib/event_handling.py
rocketlib/events.py
rocketlib/frida_script.py
rocketlib/game_objects.py
rocketlib/sdk.py
rocketlib-0.1.0.dist-info/METADATA
rocketlib-0.1.0.dist-info/WHEEL
rocketlib-0.1.0.dist-info/top_level.txt
rocketlib-0.1.0.dist-info/RECORD
