Metadata-Version: 2.4
Name: rocketlib
Version: 0.1.0
Summary: Republished version of rlsdk_python
Home-page: https://pypi.org/project/rocketlib/
Author: Ian Mattas
Author-email: ian@mattas.net
Classifier: Programming Language :: Python :: 3
Classifier: License :: OSI Approved :: MIT License
Classifier: Operating System :: OS Independent
Dynamic: author
Dynamic: author-email
Dynamic: classifier
Dynamic: home-page
Dynamic: summary
